mvr_make_package/__init__.py
mvr_make_package/cli.py
mvr_make_package/mvr-template/cookiecutter.json
mvr_make_package/mvr-template/hooks/post_gen_project.py
mvr_make_package/mvr-template/{{cookiecutter.__package_name}}/package-meta-data.xml
mvr_make_package/mvr-template/{{cookiecutter.__package_name}}/python/{{cookiecutter.__module_name}}/__init__.py
mvr_make_package/mvr-template/{{cookiecutter.__package_name}}/python/{{cookiecutter.__module_name}}/correlators/__init__.py
mvr_make_package/mvr-template/{{cookiecutter.__package_name}}/python/{{cookiecutter.__module_name}}/correlators/c_1.py
mvr_make_package/mvr-template/{{cookiecutter.__package_name}}/python/{{cookiecutter.__module_name}}/extractions/__init__.py
mvr_make_package/mvr-template/{{cookiecutter.__package_name}}/python/{{cookiecutter.__module_name}}/extractions/dx_1.py
mvr_make_package/mvr-template/{{cookiecutter.__package_name}}/python/{{cookiecutter.__module_name}}/extractions/dx_2.py
mvr_make_package/mvr-template/{{cookiecutter.__package_name}}/python/{{cookiecutter.__module_name}}/template_engines.py
mvr_make_package/mvr-template/{{cookiecutter.__package_name}}/python/{{cookiecutter.__module_name}}/yang_inputs.py
mvr_make_package/mvr-template/{{cookiecutter.__package_name}}/python/{{cookiecutter.__module_name}}/{{cookiecutter.__module_name}}.py
mvr_make_package/mvr-template/{{cookiecutter.__package_name}}/src/Makefile
mvr_make_package/mvr-template/{{cookiecutter.__package_name}}/src/yang/{{cookiecutter.__package_name}}.yang
mvr_make_package/mvr-template/{{cookiecutter.__package_name}}/templates/{{cookiecutter.__package_name}}-template.xml
mvr_make_package-0.0.4.dist-info/LICENSE
mvr_make_package-0.0.4.dist-info/METADATA
mvr_make_package-0.0.4.dist-info/WHEEL
mvr_make_package-0.0.4.dist-info/entry_points.txt
mvr_make_package-0.0.4.dist-info/RECORD
